coo_algorithm/__init__.py
coo_algorithm/coo.py
coo_algorithm-1.1.1.dist-info/METADATA
coo_algorithm-1.1.1.dist-info/WHEEL
coo_algorithm-1.1.1.dist-info/top_level.txt
coo_algorithm-1.1.1.dist-info/RECORD
