Metadata-Version: 2.4
Name: coo_algorithm
Version: 1.1.1
Summary: COO Algorithm — Canine Olfactory Optimization (COO). Surrogate-assisted, pack-based black-box optimizer.
Home-page: https://github.com/SandipGarai/coo_algorithm
Author: Sandip Garai
Author-email: Sandip Garai <sandipnicksandy@gmail.com>
License-Expression: MIT
Project-URL: Homepage, https://sandipgarai.github.io/coo_algorithm/
Project-URL: Documentation, https://github.com/SandipGarai/coo_algorithm/blob/main/README.md
Project-URL: Repository, https://github.com/SandipGarai/coo_algorithm
Project-URL: Issues, https://github.com/SandipGarai/coo_algorithm/issues
Keywords: metaheuristic,optimization,surrogate,hyperparameter-tuning,black-box,evolutionary
Classifier: Development Status :: 4 - Beta
Classifier: Intended Audience :: Science/Research
Classifier: Programming Language :: Python :: 3
Classifier: Programming Language :: Python :: 3.8
Classifier: Programming Language :: Python :: 3.9
Classifier: Programming Language :: Python :: 3.10
Classifier: Programming Language :: Python :: 3.11
Classifier: Programming Language :: Python :: 3.12
Classifier: Programming Language :: Python :: 3.13
Classifier: Topic :: Scientific/Engineering
Requires-Python: >=3.8
Requires-Dist: numpy>=1.21
Requires-Dist: scipy>=1.7
Requires-Dist: scikit-learn>=1.0
Requires-Dist: joblib>=1.1
Requires-Dist: optuna>=3.0
Provides-Extra: full
Requires-Dist: lightgbm>=4.0; extra == "full"
Requires-Dist: cma>=3.3.0; extra == "full"
Requires-Dist: optuna>=3.0; extra == "full"
Requires-Dist: matplotlib>=3.5; extra == "full"
Requires-Dist: pandas>=1.5; extra == "full"
Provides-Extra: dev
Requires-Dist: pytest>=7.0; extra == "dev"
Requires-Dist: flake8>=6.0; extra == "dev"
Requires-Dist: black>=23.0; extra == "dev"
Provides-Extra: tests
Requires-Dist: pytest>=7.0; extra == "tests"
Requires-Dist: pytest-cov; extra == "tests"
